jubladb_api/__init__.py
jubladb_api/client.py
jubladb_api/const.py
jubladb_api/metamodel.py
jubladb_api/core/__init__.py
jubladb_api/core/base_client.py
jubladb_api/core/base_entity.py
jubladb_api/core/metamodel_classes.py
jubladb_api/generated/__init__.py
jubladb_api/generated/client.py
jubladb_api/generated/groups_roles.py
jubladb_api/generated/metamodel.py
jubladb_api/generated/entities/__init__.py
jubladb_api/generated/entities/additional_address.py
jubladb_api/generated/entities/additional_email.py
jubladb_api/generated/entities/course.py
jubladb_api/generated/entities/date.py
jubladb_api/generated/entities/event.py
jubladb_api/generated/entities/event_kind.py
jubladb_api/generated/entities/event_kind_category.py
jubladb_api/generated/entities/group.py
jubladb_api/generated/entities/invoice.py
jubladb_api/generated/entities/invoice_item.py
jubladb_api/generated/entities/keys.py
jubladb_api/generated/entities/mailing_list.py
jubladb_api/generated/entities/person.py
jubladb_api/generated/entities/person_name.py
jubladb_api/generated/entities/phone_number.py
jubladb_api/generated/entities/role.py
jubladb_api/generated/entities/self_registration.py
jubladb_api/generated/entities/social_account.py
jubladb_api-0.2.2.dist-info/licenses/LICENSE
jubladb_api-0.2.2.dist-info/METADATA
jubladb_api-0.2.2.dist-info/WHEEL
jubladb_api-0.2.2.dist-info/top_level.txt
jubladb_api-0.2.2.dist-info/RECORD
