Metadata-Version: 2.4
Name: jubladb_api
Version: 0.2.2
Summary: Hitobito JSON:API
Author-email: Basil Bader <dev@basilbader.com>
License:                     GNU AFFERO GENERAL PUBLIC LICENSE
Project-URL: Repository, https://github.com/Jungwacht-Herisau/jubladb_python_api
Keywords: Hitobito JSON:API
Classifier: Programming Language :: Python :: 3
Classifier: License :: OSI Approved :: GNU Affero General Public License v3
Classifier: Operating System :: OS Independent
Requires-Python: >=3.10
License-File: LICENSE
Requires-Dist: requests>=2.32.2
Dynamic: license-file
